blindai_preview_server/__init__.py
blindai_preview_server/server.py
blindai_preview_server/version.py
blindai_preview_server-0.0.6.dist-info/METADATA
blindai_preview_server-0.0.6.dist-info/WHEEL
blindai_preview_server-0.0.6.dist-info/top_level.txt
blindai_preview_server-0.0.6.dist-info/RECORD
