Metadata-Version: 2.1
Name: blindai-preview-server
Version: 0.0.6
Summary: Server for BlindAI
Author: Mithril Security
Author-email: contact@mithrilsecurity.io
Keywords: confidential computing inference ai client enclave intel-sgx machine learning
Classifier: Programming Language :: Python :: 3
